{
  "https://wsrv.nl/?url=cam.afu-server.de/Klippeneck-CAM1.jpg": {
    "hash": "f8fef5ec68e266c81f62a8a94495c07395a55e37",
    "lastChange": 1779172750000,
    "source": "origin"
  },
  "https://wsrv.nl/?url=cam.afu-server.de/Klippeneck-CAM3.jpg": {
    "hash": "db6c16de8e933c756cb7aa890a2bc0b3e2ddb2a7",
    "lastChange": 1779172750000,
    "source": "origin"
  },
  "https://wsrv.nl/?url=donau-airport.de/donau-airport.de/webcam/cam_neu2.jpg": {
    "hash": "128c47eeff23578d42eaa7c6d7e6084f490e22a9",
    "lastChange": 1779172754000,
    "source": "origin"
  },
  "https://wsrv.nl/?url=webcam-gewerbepark.ftp-land-in-sicht.de/snap_c1.jpg": {
    "hash": "70bc62ac3bd39caa5abfeb3b9561fddb34283e47",
    "lastChange": 1779172757000,
    "source": "origin"
  },
  "https://wsrv.nl/?url=webcam.datacreate.de/feldbergblick/webcam-feldbergblick.jpg": {
    "hash": "aa1b75f416454f60039acf90da3166d12bd7af64",
    "lastChange": 1779172682000,
    "source": "origin"
  },
  "https://wsrv.nl/?url=www.feldberger-hof.de/static/webcam/fh-webcam.jpg": {
    "hash": "a2106eaf48818c68442efae83a40c83780bbadf2",
    "lastChange": 1779172211000,
    "source": "origin"
  },
  "https://wsrv.nl/?url=www.lgh-platz.de/cam/cam11.jpg": {
    "hash": "712d9746b3af56cac9a38604a3d7217f458f958b",
    "lastChange": 1779172402000,
    "source": "origin"
  },
  "https://wsrv.nl/?url=www.lgh-platz.de/cam/cam21.jpg": {
    "hash": "0ffee4b38cfc8b45a8a58328247bf58211173eb1",
    "lastChange": 1779172334000,
    "source": "origin"
  },
  "https://wsrv.nl/?url=www.lgh-platz.de/cam/cam31.jpg": {
    "hash": "7013803355e867b3b01a40811c96fa2c4a368ab4",
    "lastChange": 1779172273000,
    "source": "origin"
  },
  "https://wsrv.nl/?url=www.lgh-platz.de/cam/cam41.jpg": {
    "hash": "c92e82d1802354c0bee00fe0020b482296b91024",
    "lastChange": 1779172284000,
    "source": "origin"
  },
  "https://wsrv.nl/?url=www.lgh-platz.de/cam/cam51.jpg": {
    "hash": "a149960379fc2b629e60af266c4d30da8a9335fc",
    "lastChange": 1779172404000,
    "source": "origin"
  },
  "https://wsrv.nl/?url=www.lgh-platz.de/cam/cam61.jpg": {
    "hash": "a14e957dfd80e63980f35a754b2a95d4f88ddfb4",
    "lastChange": 1779172224000,
    "source": "origin"
  },
  "https://wsrv.nl/?url=www.lgh-platz.de/cam/cam91.jpg": {
    "hash": "37999eba516ec28316fe9d226645a64b30344751",
    "lastChange": 1779172235000,
    "source": "origin"
  },
  "https://wsrv.nl/?url=www.lsg-suedwest.de/WebCam/snapshot.jpg": {
    "hash": "cceefe98832364cb3aefcd3060d3050fe2c14369",
    "lastChange": 1779172726000,
    "source": "origin"
  },
  "https://wsrv.nl/?url=www.notschrei-loipe.de/notschrei-loipe.jpg": {
    "hash": "57408ae3d3c77f7de50eb6aa1f6507df44f1b63a",
    "lastChange": 1779172502000,
    "source": "origin"
  },
  "https://wsrv.nl/?url=www.schopfheim.de/webcam/gersbach/video.jpg": {
    "hash": "ea3404c70a0fcf0d2b70064df1869b84b2742012",
    "lastChange": 1779172738000,
    "source": "origin"
  },
  "https://wsrv.nl/?url=www.ziis.de/cam/current_WE.jpg": {
    "hash": "cc48bcddae81dd776dfabecb1768d34629aeaf6c",
    "lastChange": 1779172202000,
    "source": "origin"
  },
  "https://wsrv.nl/?url=www.ziis.de/cam/mega.jpg": {
    "hash": "60d100cf0665f695de9bd5f64262512f3cd3d850",
    "lastChange": 1779171608000,
    "source": "origin"
  }
}
