{
  "https://wsrv.nl/?url=cam.afu-server.de/Klippeneck-CAM1.jpg": {
    "hash": "1a7a989cd6c8d31cb9275fd3c4eeaaaa78bad7c2",
    "lastChange": 1782632036000,
    "source": "origin"
  },
  "https://wsrv.nl/?url=cam.afu-server.de/Klippeneck-CAM3.jpg": {
    "hash": "7e4d74ba5fe3363ea2507fd4f720c3e975b7da31",
    "lastChange": 1782632036000,
    "source": "origin"
  },
  "https://wsrv.nl/?url=donau-airport.de/donau-airport.de/webcam/cam_neu2.jpg": {
    "hash": "c454d25d7e85ac2a5b3ed51893c9fddd4e7e22f2",
    "lastChange": 1782632054000,
    "source": "origin"
  },
  "https://wsrv.nl/?url=webcam-gewerbepark.ftp-land-in-sicht.de/snap_c1.jpg": {
    "hash": "934c2c81bf0b0dd29ae90490557b9f3a238f5a4a",
    "lastChange": 1782632065000,
    "source": "origin"
  },
  "https://wsrv.nl/?url=webcam.datacreate.de/feldbergblick/webcam-feldbergblick.jpg": {
    "hash": "b330a6e0bd50125a31dd30e112df2b05a0d337fb",
    "lastChange": 1782632043000,
    "source": "origin"
  },
  "https://wsrv.nl/?url=www.feldberger-hof.de/static/webcam/fh-webcam.jpg": {
    "hash": "d8c2b624cfd13823019203b1df43d4f6702516cd",
    "lastChange": 1782631808000,
    "source": "origin"
  },
  "https://wsrv.nl/?url=www.lgh-platz.de/cam/cam11.jpg": {
    "hash": "6ac5a3e245c630a39cd8ed35ff0a81799b47d6f5",
    "lastChange": 1782631823000,
    "source": "origin"
  },
  "https://wsrv.nl/?url=www.lgh-platz.de/cam/cam21.jpg": {
    "hash": "139b3b80a9d73bcb73fc125f9d3434eac05748e8",
    "lastChange": 1782631818000,
    "source": "origin"
  },
  "https://wsrv.nl/?url=www.lgh-platz.de/cam/cam31.jpg": {
    "hash": "c4c9a07501c43ea78128df831b63df4dd2a40b1c",
    "lastChange": 1782631811000,
    "source": "origin"
  },
  "https://wsrv.nl/?url=www.lgh-platz.de/cam/cam41.jpg": {
    "hash": "f1c770dde3856ecc3dcc94259f9f725440831a03",
    "lastChange": 1782631873000,
    "source": "origin"
  },
  "https://wsrv.nl/?url=www.lgh-platz.de/cam/cam51.jpg": {
    "hash": "0eeac25c61ef772a1e024d40c8b834e1d5eec39c",
    "lastChange": 1782546145000,
    "source": "origin"
  },
  "https://wsrv.nl/?url=www.lgh-platz.de/cam/cam61.jpg": {
    "hash": "1c42ba9125e58305c87518577bd068461ff12350",
    "lastChange": 1782631996000,
    "source": "origin"
  },
  "https://wsrv.nl/?url=www.lgh-platz.de/cam/cam91.jpg": {
    "hash": "90d3a6d0fbda9a2fc61b551674f77b34d591f6ff",
    "lastChange": 1782632071000,
    "source": "origin"
  },
  "https://wsrv.nl/?url=www.lsg-suedwest.de/WebCam/snapshot.jpg": {
    "hash": "8f7d2e8f024551337c655833eac903cd10f24c2d",
    "lastChange": 1782632046000,
    "source": "origin"
  },
  "https://wsrv.nl/?url=www.notschrei-loipe.de/notschrei-loipe.jpg": {
    "hash": "936a6c1dc1e046ab58baaff7d94bd9dab5e07944",
    "lastChange": 1782631803000,
    "source": "origin"
  },
  "https://wsrv.nl/?url=www.schopfheim.de/webcam/gersbach/video.jpg": {
    "hash": "e6ad632b829f7ab7d05a035f6615b04ea3a3ebd5",
    "lastChange": 1782631512000,
    "source": "origin"
  },
  "https://wsrv.nl/?url=www.ziis.de/cam/current_WE.jpg": {
    "hash": "14d1242603e6f79bf3338de66ba0133e7b8cc76c",
    "lastChange": 1782631807000,
    "source": "origin"
  },
  "https://wsrv.nl/?url=www.ziis.de/cam/mega.jpg": {
    "hash": "76c9e6b7292e6fb6e77524c83314be572077235c",
    "lastChange": 1782631209000,
    "source": "origin"
  }
}
