{
  "https://wsrv.nl/?url=cam.afu-server.de/Klippeneck-CAM1.jpg": {
    "hash": "1a12f8630d96359d3295027374a598191678e41c",
    "lastChange": 1781424858000,
    "source": "origin"
  },
  "https://wsrv.nl/?url=cam.afu-server.de/Klippeneck-CAM3.jpg": {
    "hash": "9270f7e18072c195a3d5bf201dd5e12b1fc3cec2",
    "lastChange": 1781424857000,
    "source": "origin"
  },
  "https://wsrv.nl/?url=donau-airport.de/donau-airport.de/webcam/cam_neu2.jpg": {
    "hash": "ccb712b5bf953cbf00044cfb1ab022bdf484d17f",
    "lastChange": 1781424854000,
    "source": "origin"
  },
  "https://wsrv.nl/?url=webcam-gewerbepark.ftp-land-in-sicht.de/snap_c1.jpg": {
    "hash": "bf0bae64320ef85f39db671d397a55e378c72bd1",
    "lastChange": 1781424853000,
    "source": "origin"
  },
  "https://wsrv.nl/?url=webcam.datacreate.de/feldbergblick/webcam-feldbergblick.jpg": {
    "hash": "c3646841966ca62a08e38499f61975dc51005b13",
    "lastChange": 1781424843000,
    "source": "origin"
  },
  "https://wsrv.nl/?url=www.feldberger-hof.de/static/webcam/fh-webcam.jpg": {
    "hash": "60077e8ecc40d5dd9da0462f4e73928fd0add778",
    "lastChange": 1781424608000,
    "source": "origin"
  },
  "https://wsrv.nl/?url=www.lgh-platz.de/cam/cam11.jpg": {
    "hash": "71a99ff57b5408008365942bbb7951c0f4902678",
    "lastChange": 1781424824000,
    "source": "origin"
  },
  "https://wsrv.nl/?url=www.lgh-platz.de/cam/cam21.jpg": {
    "hash": "6c7d831246429701be3eb9fb6794dc91735ffeea",
    "lastChange": 1781424734000,
    "source": "origin"
  },
  "https://wsrv.nl/?url=www.lgh-platz.de/cam/cam31.jpg": {
    "hash": "ddad041fca69801a6bb566eaf19dbb1e6d03bdaf",
    "lastChange": 1781424611000,
    "source": "origin"
  },
  "https://wsrv.nl/?url=www.lgh-platz.de/cam/cam41.jpg": {
    "hash": "bd7ec006b435a3ec8f68f0dd20b1fea9fefd29b3",
    "lastChange": 1781424673000,
    "source": "origin"
  },
  "https://wsrv.nl/?url=www.lgh-platz.de/cam/cam51.jpg": {
    "hash": "31da3e945b09c7b77d96ae0c5e7978968757a73d",
    "lastChange": 1781422940000,
    "source": "origin"
  },
  "https://wsrv.nl/?url=www.lgh-platz.de/cam/cam61.jpg": {
    "hash": "977357235bd1b7fe7563ccf21f2c32bca38e890d",
    "lastChange": 1781424799000,
    "source": "origin"
  },
  "https://wsrv.nl/?url=www.lgh-platz.de/cam/cam91.jpg": {
    "hash": "76f5ef68aaa3e4adcd30e86b0b47328eaff21850",
    "lastChange": 1781424871000,
    "source": "origin"
  },
  "https://wsrv.nl/?url=www.lsg-suedwest.de/WebCam/snapshot.jpg": {
    "hash": "2baacdd4e840bce2903431be5f9a8e7646cd55d6",
    "lastChange": 1781424849000,
    "source": "origin"
  },
  "https://wsrv.nl/?url=www.notschrei-loipe.de/notschrei-loipe.jpg": {
    "hash": "e0af3b20370403b410de96020adfb51ff1c3662f",
    "lastChange": 1781424603000,
    "source": "origin"
  },
  "https://wsrv.nl/?url=www.schopfheim.de/webcam/gersbach/video.jpg": {
    "hash": "fb6b99bb6356e47adf4ccf73c8a7bbe2c7c5fb38",
    "lastChange": 1781424832000,
    "source": "origin"
  },
  "https://wsrv.nl/?url=www.ziis.de/cam/current_WE.jpg": {
    "hash": "52185375d2fcbf7f7ad7a42336435f40f434267a",
    "lastChange": 1781424605000,
    "source": "origin"
  },
  "https://wsrv.nl/?url=www.ziis.de/cam/mega.jpg": {
    "hash": "b38976c986246d4fe999c14bfc3d8d59c4117e0c",
    "lastChange": 1781424010000,
    "source": "origin"
  }
}
