{
  "https://wsrv.nl/?url=cam.afu-server.de/Klippeneck-CAM1.jpg": {
    "hash": "7b2f746be1159b079e19ccd5d17028fe341d114e",
    "lastChange": 1781799254000,
    "source": "origin"
  },
  "https://wsrv.nl/?url=cam.afu-server.de/Klippeneck-CAM3.jpg": {
    "hash": "5a6129d8e66a01d3dc1a81b5b5dd01e6543a7535",
    "lastChange": 1781799254000,
    "source": "origin"
  },
  "https://wsrv.nl/?url=donau-airport.de/donau-airport.de/webcam/cam_neu2.jpg": {
    "hash": "45fb7a7ccdc1d1dc245031e42ebcdcb961c45a6b",
    "lastChange": 1781799254000,
    "source": "origin"
  },
  "https://wsrv.nl/?url=webcam-gewerbepark.ftp-land-in-sicht.de/snap_c1.jpg": {
    "hash": "938f2ddebd5dbeb95d89da04b9cba7051e2637ef",
    "lastChange": 1781799277000,
    "source": "origin"
  },
  "https://wsrv.nl/?url=webcam.datacreate.de/feldbergblick/webcam-feldbergblick.jpg": {
    "hash": "a6ec5b488f438ce99b2782b975a7223a07cee495",
    "lastChange": 1781799243000,
    "source": "origin"
  },
  "https://wsrv.nl/?url=www.feldberger-hof.de/static/webcam/fh-webcam.jpg": {
    "hash": "b76009f829cfd550958bc01fcdc73f30c17e5005",
    "lastChange": 1781799008000,
    "source": "origin"
  },
  "https://wsrv.nl/?url=www.lgh-platz.de/cam/cam11.jpg": {
    "hash": "bcc455e9067c4c316fcd992cb979c243e4f75c5d",
    "lastChange": 1781798613000,
    "source": "origin"
  },
  "https://wsrv.nl/?url=www.lgh-platz.de/cam/cam21.jpg": {
    "hash": "1bca468041358644639cf3fd46979938ba4e5e98",
    "lastChange": 1781799135000,
    "source": "origin"
  },
  "https://wsrv.nl/?url=www.lgh-platz.de/cam/cam31.jpg": {
    "hash": "c4231356e082132cb096efee92e76d551a4958c0",
    "lastChange": 1781799011000,
    "source": "origin"
  },
  "https://wsrv.nl/?url=www.lgh-platz.de/cam/cam41.jpg": {
    "hash": "e5e26ec665bce4df18fe0cde0f72950721a73967",
    "lastChange": 1781799074000,
    "source": "origin"
  },
  "https://wsrv.nl/?url=www.lgh-platz.de/cam/cam51.jpg": {
    "hash": "468482acff477c97af240e8456f0999cb328256c",
    "lastChange": 1781764216000,
    "source": "origin"
  },
  "https://wsrv.nl/?url=www.lgh-platz.de/cam/cam61.jpg": {
    "hash": "06f413cc45f1c2bc83b419f214013ae2594282db",
    "lastChange": 1781798596000,
    "source": "origin"
  },
  "https://wsrv.nl/?url=www.lgh-platz.de/cam/cam91.jpg": {
    "hash": "60259c1a19b3496f28e8465d4deafd96cfeb2459",
    "lastChange": 1781799262000,
    "source": "origin"
  },
  "https://wsrv.nl/?url=www.lsg-suedwest.de/WebCam/snapshot.jpg": {
    "hash": "16eb9e98f5e936e3775c8694b32b1bc07b1423e5",
    "lastChange": 1781799269000,
    "source": "origin"
  },
  "https://wsrv.nl/?url=www.notschrei-loipe.de/notschrei-loipe.jpg": {
    "hash": "70fe538f5ed19b06803aa740c94daa944491d8fb",
    "lastChange": 1781799003000,
    "source": "origin"
  },
  "https://wsrv.nl/?url=www.schopfheim.de/webcam/gersbach/video.jpg": {
    "hash": "6ccc3978167a151631e3baf5947fdbf4741e6062",
    "lastChange": 1781799273000,
    "source": "origin"
  },
  "https://wsrv.nl/?url=www.ziis.de/cam/current_WE.jpg": {
    "hash": "135e901d92a406da61ccae3d64fe129f4b7edf78",
    "lastChange": 1781799005000,
    "source": "origin"
  },
  "https://wsrv.nl/?url=www.ziis.de/cam/mega.jpg": {
    "hash": "3d86790223be2996da335832c4268252d5fdc32d",
    "lastChange": 1781798410000,
    "source": "origin"
  }
}
