{
  "https://wsrv.nl/?url=cam.afu-server.de/Klippeneck-CAM1.jpg": {
    "hash": "1f698d4bdd485a75269713683b671cebb5bb18c3",
    "lastChange": 1779156847000,
    "source": "origin"
  },
  "https://wsrv.nl/?url=cam.afu-server.de/Klippeneck-CAM3.jpg": {
    "hash": "e05657bf52cfa1a2ce7d901bd01fe112a2bb70e2",
    "lastChange": 1779156847000,
    "source": "origin"
  },
  "https://wsrv.nl/?url=donau-airport.de/donau-airport.de/webcam/cam_neu2.jpg": {
    "hash": "636aae93cbe32e12d31ef3db3f5d65b31afd737a",
    "lastChange": 1779156857000,
    "source": "origin"
  },
  "https://wsrv.nl/?url=webcam-gewerbepark.ftp-land-in-sicht.de/snap_c1.jpg": {
    "hash": "a1768d13e29b54041b58e78836ae347196c7c8f4",
    "lastChange": 1779156857000,
    "source": "origin"
  },
  "https://wsrv.nl/?url=webcam.datacreate.de/feldbergblick/webcam-feldbergblick.jpg": {
    "hash": "6e809d8c996d99245d13d148c4c6c3cb83f7126c",
    "lastChange": 1779156841000,
    "source": "origin"
  },
  "https://wsrv.nl/?url=www.feldberger-hof.de/static/webcam/fh-webcam.jpg": {
    "hash": "f865d75cde16622a909c78ff67646716a801abb6",
    "lastChange": 1779130810000,
    "source": "origin"
  },
  "https://wsrv.nl/?url=www.lgh-platz.de/cam/cam11.jpg": {
    "hash": "5c77c3aeb1d05c6d93b2b438927fa0ce7865e43b",
    "lastChange": 1779156802000,
    "source": "origin"
  },
  "https://wsrv.nl/?url=www.lgh-platz.de/cam/cam21.jpg": {
    "hash": "89b49eec02dea4a7ea1f8a471f5938fc1773b2d8",
    "lastChange": 1779156328000,
    "source": "origin"
  },
  "https://wsrv.nl/?url=www.lgh-platz.de/cam/cam31.jpg": {
    "hash": "b256e6705714e90b70b6b42c8ee8cf58539c46cc",
    "lastChange": 1779156860000,
    "source": "origin"
  },
  "https://wsrv.nl/?url=www.lgh-platz.de/cam/cam41.jpg": {
    "hash": "58fcbb71daa5d31298e3b65fbcad0099bcb6a66a",
    "lastChange": 1779156712000,
    "source": "origin"
  },
  "https://wsrv.nl/?url=www.lgh-platz.de/cam/cam51.jpg": {
    "hash": "385a3187f008c7ddb62633bbe273bbfefabfe1f4",
    "lastChange": 1779156679000,
    "source": "origin"
  },
  "https://wsrv.nl/?url=www.lgh-platz.de/cam/cam61.jpg": {
    "hash": "bba10b68321e39395bf122a1a2d7ff9908c44b46",
    "lastChange": 1779156273000,
    "source": "origin"
  },
  "https://wsrv.nl/?url=www.lgh-platz.de/cam/cam91.jpg": {
    "hash": "f878991f15b4d9bd274957cdf1a089cedbb9abeb",
    "lastChange": 1779156643000,
    "source": "origin"
  },
  "https://wsrv.nl/?url=www.lsg-suedwest.de/WebCam/snapshot.jpg": {
    "hash": "7e29d17ee0c9ae747106038a763b777699427af2",
    "lastChange": 1779156818000,
    "source": "origin"
  },
  "https://wsrv.nl/?url=www.notschrei-loipe.de/notschrei-loipe.jpg": {
    "hash": "c087589af5d02784eab4aa8e85d472e57ef543be",
    "lastChange": 1779156603000,
    "source": "origin"
  },
  "https://wsrv.nl/?url=www.schopfheim.de/webcam/gersbach/video.jpg": {
    "hash": "83e3c09071693d6672a05750e0c7f5b0384ba427",
    "lastChange": 1779156819000,
    "source": "origin"
  },
  "https://wsrv.nl/?url=www.ziis.de/cam/current_WE.jpg": {
    "hash": "818cc471cd082ee6d385222cd5d9884ddc5f4daf",
    "lastChange": 1779156605000,
    "source": "origin"
  },
  "https://wsrv.nl/?url=www.ziis.de/cam/mega.jpg": {
    "hash": "df9c19bd5a407834cbb95f5e81274c92800cc6a5",
    "lastChange": 1779156008000,
    "source": "origin"
  }
}
