{
  "https://wsrv.nl/?url=cam.afu-server.de/Klippeneck-CAM1.jpg": {
    "hash": "84fe4d6704278c64d00c9b30fe54533cfcb9e71b",
    "lastChange": 1781784249000,
    "source": "origin"
  },
  "https://wsrv.nl/?url=cam.afu-server.de/Klippeneck-CAM3.jpg": {
    "hash": "473fc393f67b7c19077f3d605a39959bb695cba8",
    "lastChange": 1781784251000,
    "source": "origin"
  },
  "https://wsrv.nl/?url=donau-airport.de/donau-airport.de/webcam/cam_neu2.jpg": {
    "hash": "04b39bb01d2a7642d604a242d51e9e69e9d6c1a0",
    "lastChange": 1781784254000,
    "source": "origin"
  },
  "https://wsrv.nl/?url=webcam-gewerbepark.ftp-land-in-sicht.de/snap_c1.jpg": {
    "hash": "63398fe72056984f095f0357b041c06139b60476",
    "lastChange": 1781784263000,
    "source": "origin"
  },
  "https://wsrv.nl/?url=webcam.datacreate.de/feldbergblick/webcam-feldbergblick.jpg": {
    "hash": "b5fec0a2ab8fe3efa799f8df19b177be4aac7f0b",
    "lastChange": 1781784243000,
    "source": "origin"
  },
  "https://wsrv.nl/?url=www.feldberger-hof.de/static/webcam/fh-webcam.jpg": {
    "hash": "558ed5896b7ea6382a5a831f6046c2ea68a0a6c1",
    "lastChange": 1781784009000,
    "source": "origin"
  },
  "https://wsrv.nl/?url=www.lgh-platz.de/cam/cam11.jpg": {
    "hash": "bbfbfe4507527c6f4c3f5f19cb4c5e400dc23764",
    "lastChange": 1781783594000,
    "source": "origin"
  },
  "https://wsrv.nl/?url=www.lgh-platz.de/cam/cam21.jpg": {
    "hash": "c4962befd356e99fa1a2ebb531b62fb7ff0fa666",
    "lastChange": 1781784138000,
    "source": "origin"
  },
  "https://wsrv.nl/?url=www.lgh-platz.de/cam/cam31.jpg": {
    "hash": "f0f47c9512b8581be12e74e78ec690a20147ceb6",
    "lastChange": 1781784011000,
    "source": "origin"
  },
  "https://wsrv.nl/?url=www.lgh-platz.de/cam/cam41.jpg": {
    "hash": "810072c0ce8bb1970328076b324b25b39b27c449",
    "lastChange": 1781784073000,
    "source": "origin"
  },
  "https://wsrv.nl/?url=www.lgh-platz.de/cam/cam51.jpg": {
    "hash": "468482acff477c97af240e8456f0999cb328256c",
    "lastChange": 1781764216000,
    "source": "origin"
  },
  "https://wsrv.nl/?url=www.lgh-platz.de/cam/cam61.jpg": {
    "hash": "852e75e1289f50943b4218d7c7df1e559f85d0d3",
    "lastChange": 1781784198000,
    "source": "origin"
  },
  "https://wsrv.nl/?url=www.lgh-platz.de/cam/cam91.jpg": {
    "hash": "494447852fab96bc5f04031cce971fbb952d5a8f",
    "lastChange": 1781783662000,
    "source": "origin"
  },
  "https://wsrv.nl/?url=www.lsg-suedwest.de/WebCam/snapshot.jpg": {
    "hash": "54116af6bf167ac47a56ed014a1b408c1f8afa89",
    "lastChange": 1781784260000,
    "source": "origin"
  },
  "https://wsrv.nl/?url=www.notschrei-loipe.de/notschrei-loipe.jpg": {
    "hash": "d71ea05352f4bdcf8cdd5d386c0e8d37621f67e6",
    "lastChange": 1781784003000,
    "source": "origin"
  },
  "https://wsrv.nl/?url=www.schopfheim.de/webcam/gersbach/video.jpg": {
    "hash": "b6fcc26f14eed2bda5591ebe28021f6889feff44",
    "lastChange": 1781784273000,
    "source": "origin"
  },
  "https://wsrv.nl/?url=www.ziis.de/cam/current_WE.jpg": {
    "hash": "cab3cf0ea544cb60bc56ba3fab08133681b0d6f3",
    "lastChange": 1781784007000,
    "source": "origin"
  },
  "https://wsrv.nl/?url=www.ziis.de/cam/mega.jpg": {
    "hash": "a3bdb00b453a99d9813d3fe48f9cf1458314d7a1",
    "lastChange": 1781784009000,
    "source": "origin"
  }
}
