{
  "https://wsrv.nl/?url=cam.afu-server.de/Klippeneck-CAM1.jpg": {
    "hash": "f7a98aecd0053ca9e8097320eb4c1771096ef82f",
    "lastChange": 1781854737000,
    "source": "origin"
  },
  "https://wsrv.nl/?url=cam.afu-server.de/Klippeneck-CAM3.jpg": {
    "hash": "a1aa723b568adfa974535066020f37309bd02fc9",
    "lastChange": 1781854738000,
    "source": "origin"
  },
  "https://wsrv.nl/?url=donau-airport.de/donau-airport.de/webcam/cam_neu2.jpg": {
    "hash": "7d177bcd07a787bc55077c8e05d022e84f37d8a2",
    "lastChange": 1781854754000,
    "source": "origin"
  },
  "https://wsrv.nl/?url=webcam-gewerbepark.ftp-land-in-sicht.de/snap_c1.jpg": {
    "hash": "39c49e9beb20e01ee0b4f56f6ecd681c5ddf8745",
    "lastChange": 1781854761000,
    "source": "origin"
  },
  "https://wsrv.nl/?url=webcam.datacreate.de/feldbergblick/webcam-feldbergblick.jpg": {
    "hash": "9827ff180e90a36cdff0b7bd3b42f3c8ad7725d3",
    "lastChange": 1781854682000,
    "source": "origin"
  },
  "https://wsrv.nl/?url=www.feldberger-hof.de/static/webcam/fh-webcam.jpg": {
    "hash": "0c18fa0cd50cd71b7c2838f3a35cf2c5b149697c",
    "lastChange": 1781854209000,
    "source": "origin"
  },
  "https://wsrv.nl/?url=www.lgh-platz.de/cam/cam11.jpg": {
    "hash": "fbc5c135b17cec4329868c4416e9a55c0e7b3ca5",
    "lastChange": 1781854744000,
    "source": "origin"
  },
  "https://wsrv.nl/?url=www.lgh-platz.de/cam/cam21.jpg": {
    "hash": "fde03e8c6dfca5c8e3e78bc87f004fc38d76e3a4",
    "lastChange": 1781854333000,
    "source": "origin"
  },
  "https://wsrv.nl/?url=www.lgh-platz.de/cam/cam31.jpg": {
    "hash": "1b1a998fb1f521fb37e5b860d596d02ac4c10e7b",
    "lastChange": 1781854211000,
    "source": "origin"
  },
  "https://wsrv.nl/?url=www.lgh-platz.de/cam/cam41.jpg": {
    "hash": "0be846eafea250c7843a77b87b1bc6d39b2c10da",
    "lastChange": 1781854274000,
    "source": "origin"
  },
  "https://wsrv.nl/?url=www.lgh-platz.de/cam/cam51.jpg": {
    "hash": "468482acff477c97af240e8456f0999cb328256c",
    "lastChange": 1781764216000,
    "source": "origin"
  },
  "https://wsrv.nl/?url=www.lgh-platz.de/cam/cam61.jpg": {
    "hash": "d10ed2a1f4b0b000c886dc9f5c2ac2281c78ae8a",
    "lastChange": 1781854534000,
    "source": "origin"
  },
  "https://wsrv.nl/?url=www.lgh-platz.de/cam/cam91.jpg": {
    "hash": "b63d7080011523d356b70a995d7b4f7c9fe805d9",
    "lastChange": 1781854462000,
    "source": "origin"
  },
  "https://wsrv.nl/?url=www.lsg-suedwest.de/WebCam/snapshot.jpg": {
    "hash": "32c9e023efe7ac270f68e083a57ea6717e0e3a42",
    "lastChange": 1781854739000,
    "source": "origin"
  },
  "https://wsrv.nl/?url=www.notschrei-loipe.de/notschrei-loipe.jpg": {
    "hash": "6f3fbd40006b43447a3428005450f5b21a285602",
    "lastChange": 1781854502000,
    "source": "origin"
  },
  "https://wsrv.nl/?url=www.schopfheim.de/webcam/gersbach/video.jpg": {
    "hash": "898eb3a532e1bbd86776ff83effbf0c895246a94",
    "lastChange": 1781854480000,
    "source": "origin"
  },
  "https://wsrv.nl/?url=www.ziis.de/cam/current_WE.jpg": {
    "hash": "fcc4d51d62682b84e76576da1bf00f1ffdde794a",
    "lastChange": 1781854205000,
    "source": "origin"
  },
  "https://wsrv.nl/?url=www.ziis.de/cam/mega.jpg": {
    "hash": "91772fe97fc6e52a29be1a3c4db51f9f1d427960",
    "lastChange": 1781853607000,
    "source": "origin"
  }
}
