{
  "https://wsrv.nl/?url=cam.afu-server.de/Klippeneck-CAM1.jpg": {
    "hash": "b4404091bbf694613a15c3be98380394df32790c",
    "lastChange": 1782116936000,
    "source": "origin"
  },
  "https://wsrv.nl/?url=cam.afu-server.de/Klippeneck-CAM3.jpg": {
    "hash": "82cc64f821048b046d5bc21436c95d46149c428a",
    "lastChange": 1782116937000,
    "source": "origin"
  },
  "https://wsrv.nl/?url=donau-airport.de/donau-airport.de/webcam/cam_neu2.jpg": {
    "hash": "fc42d54427ce2c52da76ab853fba78ec86042dcf",
    "lastChange": 1782116954000,
    "source": "origin"
  },
  "https://wsrv.nl/?url=webcam-gewerbepark.ftp-land-in-sicht.de/snap_c1.jpg": {
    "hash": "7bd06dd171b8af9ae5fe7dd4954bb8f73e2f8185",
    "lastChange": 1782116958000,
    "source": "origin"
  },
  "https://wsrv.nl/?url=webcam.datacreate.de/feldbergblick/webcam-feldbergblick.jpg": {
    "hash": "78c3eb4b031718b14d819e60d32994147417fa48",
    "lastChange": 1782116883000,
    "source": "origin"
  },
  "https://wsrv.nl/?url=www.feldberger-hof.de/static/webcam/fh-webcam.jpg": {
    "hash": "d2117308fa59e1d0d94b227d3afd46ae1d3227ea",
    "lastChange": 1782116410000,
    "source": "origin"
  },
  "https://wsrv.nl/?url=www.lgh-platz.de/cam/cam11.jpg": {
    "hash": "28d2fb0f89e7831e2ea3608b7235c8f41f980100",
    "lastChange": 1782030201000,
    "source": "origin"
  },
  "https://wsrv.nl/?url=www.lgh-platz.de/cam/cam21.jpg": {
    "hash": "f41128e08bef43e81bfc7b7f8ea746ffcd6d2836",
    "lastChange": 1782116533000,
    "source": "origin"
  },
  "https://wsrv.nl/?url=www.lgh-platz.de/cam/cam31.jpg": {
    "hash": "d1b4c8106021813fe06dcd964d96aa39198b9e48",
    "lastChange": 1782116411000,
    "source": "origin"
  },
  "https://wsrv.nl/?url=www.lgh-platz.de/cam/cam41.jpg": {
    "hash": "6408a52d0f7dfd4e6882284ba87a86ea62ba8641",
    "lastChange": 1782116475000,
    "source": "origin"
  },
  "https://wsrv.nl/?url=www.lgh-platz.de/cam/cam51.jpg": {
    "hash": "fc17efdc5a14f650c35afeb12340c4d265f76f6d",
    "lastChange": 1782105139000,
    "source": "origin"
  },
  "https://wsrv.nl/?url=www.lgh-platz.de/cam/cam61.jpg": {
    "hash": "e11611dc6abab04f76a17d8098b61c5f046ac756",
    "lastChange": 1782116662000,
    "source": "origin"
  },
  "https://wsrv.nl/?url=www.lgh-platz.de/cam/cam91.jpg": {
    "hash": "876edbb41426fff2c3062de5e053c274f5eee5f9",
    "lastChange": 1782116673000,
    "source": "origin"
  },
  "https://wsrv.nl/?url=www.lsg-suedwest.de/WebCam/snapshot.jpg": {
    "hash": "2af81114ed6b61da5f5380d257bcfa17f9efb54a",
    "lastChange": 1782116955000,
    "source": "origin"
  },
  "https://wsrv.nl/?url=www.notschrei-loipe.de/notschrei-loipe.jpg": {
    "hash": "65af0c6aba814867ea502d8342983b54259d401e",
    "lastChange": 1782116702000,
    "source": "origin"
  },
  "https://wsrv.nl/?url=www.schopfheim.de/webcam/gersbach/video.jpg": {
    "hash": "2f7c0d9d3b65fec8314b42028b36b79064477ddf",
    "lastChange": 1782116966000,
    "source": "origin"
  },
  "https://wsrv.nl/?url=www.ziis.de/cam/current_WE.jpg": {
    "hash": "ecd818e240078bb9c25fb154334f7577785dfbaa",
    "lastChange": 1782116406000,
    "source": "origin"
  },
  "https://wsrv.nl/?url=www.ziis.de/cam/mega.jpg": {
    "hash": "0948ee26eeb223da6250b64ec572277673df3ce9",
    "lastChange": 1782116408000,
    "source": "origin"
  }
}
