{
  "https://wsrv.nl/?url=cam.afu-server.de/Klippeneck-CAM1.jpg": {
    "hash": "44bab89ce7048a20cc3d7b50e3071dd968d22535",
    "lastChange": 1780663457000,
    "source": "origin"
  },
  "https://wsrv.nl/?url=cam.afu-server.de/Klippeneck-CAM3.jpg": {
    "hash": "4883f331b0a4e0f6d404bdf433e2034c31c6f3ed",
    "lastChange": 1780663457000,
    "source": "origin"
  },
  "https://wsrv.nl/?url=donau-airport.de/donau-airport.de/webcam/cam_neu2.jpg": {
    "hash": "0de87bcfcb16cbe91cd5d25c651c0a740e6092a7",
    "lastChange": 1780663454000,
    "source": "origin"
  },
  "https://wsrv.nl/?url=webcam-gewerbepark.ftp-land-in-sicht.de/snap_c1.jpg": {
    "hash": "026e02b81b795f7830910baec1d081ec2c06cdc9",
    "lastChange": 1780663449000,
    "source": "origin"
  },
  "https://wsrv.nl/?url=webcam.datacreate.de/feldbergblick/webcam-feldbergblick.jpg": {
    "hash": "4accd672a652ea4100632cd40df0fb8afc1477a2",
    "lastChange": 1780663442000,
    "source": "origin"
  },
  "https://wsrv.nl/?url=www.feldberger-hof.de/static/webcam/fh-webcam.jpg": {
    "hash": "6741ed66f2d50cd75483fcf9c82acfcf14dd4698",
    "lastChange": 1780663208000,
    "source": "origin"
  },
  "https://wsrv.nl/?url=www.lgh-platz.de/cam/cam11.jpg": {
    "hash": "42c03bfa966da36de3e71b1815222b5c9d36f93d",
    "lastChange": 1780663412000,
    "source": "origin"
  },
  "https://wsrv.nl/?url=www.lgh-platz.de/cam/cam21.jpg": {
    "hash": "86fe8e9dfc38033a97e65b0a3448a5e22022a4b6",
    "lastChange": 1780663338000,
    "source": "origin"
  },
  "https://wsrv.nl/?url=www.lgh-platz.de/cam/cam31.jpg": {
    "hash": "de0d8f5971444c580d74476cd98f4094ef52a2e1",
    "lastChange": 1780663289000,
    "source": "origin"
  },
  "https://wsrv.nl/?url=www.lgh-platz.de/cam/cam41.jpg": {
    "hash": "d5f919eb04beab63381e33ea3e75d219934f15b8",
    "lastChange": 1780660280000,
    "source": "origin"
  },
  "https://wsrv.nl/?url=www.lgh-platz.de/cam/cam51.jpg": {
    "hash": "8d09b74b335b2834fb27320a70b1e9e8d1ed3472",
    "lastChange": 1780662200000,
    "source": "origin"
  },
  "https://wsrv.nl/?url=www.lgh-platz.de/cam/cam61.jpg": {
    "hash": "e4a84664448e1b6a338f8ffde660cafe734546d7",
    "lastChange": 1780663297000,
    "source": "origin"
  },
  "https://wsrv.nl/?url=www.lgh-platz.de/cam/cam91.jpg": {
    "hash": "66cfe67064311772ed0f0e3f3bb5ab51fdfa4a2d",
    "lastChange": 1780663235000,
    "source": "origin"
  },
  "https://wsrv.nl/?url=www.lsg-suedwest.de/WebCam/snapshot.jpg": {
    "hash": "2c261185c269c35731f9e77dc8a89c948d9ffc30",
    "lastChange": 1780663439000,
    "source": "origin"
  },
  "https://wsrv.nl/?url=www.notschrei-loipe.de/notschrei-loipe.jpg": {
    "hash": "e49372f37fe577b30a423441f645b046e974ea9a",
    "lastChange": 1780663203000,
    "source": "origin"
  },
  "https://wsrv.nl/?url=www.schopfheim.de/webcam/gersbach/video.jpg": {
    "hash": "87e2914ddbb46a65c3fe2b97384706e3a8f2558e",
    "lastChange": 1780663442000,
    "source": "origin"
  },
  "https://wsrv.nl/?url=www.ziis.de/cam/current_WE.jpg": {
    "hash": "834703d3eb832d3442eb4065aca3409624733506",
    "lastChange": 1780663204000,
    "source": "origin"
  },
  "https://wsrv.nl/?url=www.ziis.de/cam/mega.jpg": {
    "hash": "510ee6780b3be068934dcab0020d386163b41b29",
    "lastChange": 1780663207000,
    "source": "origin"
  }
}
