{
  "https://wsrv.nl/?url=cam.afu-server.de/Klippeneck-CAM1.jpg": {
    "hash": "0fbbb48af5bcbcfc74e0e3655bad42b6a7c0b7bc",
    "lastChange": 1781941459000,
    "source": "origin"
  },
  "https://wsrv.nl/?url=cam.afu-server.de/Klippeneck-CAM3.jpg": {
    "hash": "8382780876dd664d4203979ebf2a82b217870f0b",
    "lastChange": 1781941456000,
    "source": "origin"
  },
  "https://wsrv.nl/?url=donau-airport.de/donau-airport.de/webcam/cam_neu2.jpg": {
    "hash": "00f72d4f80685df54a5ff9ab766e7a95a553f33c",
    "lastChange": 1781941454000,
    "source": "origin"
  },
  "https://wsrv.nl/?url=webcam-gewerbepark.ftp-land-in-sicht.de/snap_c1.jpg": {
    "hash": "fc21318c000f0c90d320c5f80fe05fae28049447",
    "lastChange": 1781941462000,
    "source": "origin"
  },
  "https://wsrv.nl/?url=webcam.datacreate.de/feldbergblick/webcam-feldbergblick.jpg": {
    "hash": "ffbb79b1ceeabd0fced9963832dcf7badb5cf242",
    "lastChange": 1781941442000,
    "source": "origin"
  },
  "https://wsrv.nl/?url=www.feldberger-hof.de/static/webcam/fh-webcam.jpg": {
    "hash": "a3ea143113b949af01882892ab4690dc42516b61",
    "lastChange": 1781941208000,
    "source": "origin"
  },
  "https://wsrv.nl/?url=www.lgh-platz.de/cam/cam11.jpg": {
    "hash": "2dc306a10c3725685a5bed9be9507a8ae0437b24",
    "lastChange": 1781940800000,
    "source": "origin"
  },
  "https://wsrv.nl/?url=www.lgh-platz.de/cam/cam21.jpg": {
    "hash": "4432b620ce5f67dd9ff5f8e060c7c4e9ef273d7a",
    "lastChange": 1781941338000,
    "source": "origin"
  },
  "https://wsrv.nl/?url=www.lgh-platz.de/cam/cam31.jpg": {
    "hash": "ed46c174d7e5c8bd7ae2677f671b87c7aa6639ed",
    "lastChange": 1781941211000,
    "source": "origin"
  },
  "https://wsrv.nl/?url=www.lgh-platz.de/cam/cam41.jpg": {
    "hash": "b8b7e5e79ef35d16f56f9ce776d2c9ee43a00462",
    "lastChange": 1781941273000,
    "source": "origin"
  },
  "https://wsrv.nl/?url=www.lgh-platz.de/cam/cam51.jpg": {
    "hash": "56cc3c16d02b95091f671f6757934779c286c520",
    "lastChange": 1781861782000,
    "source": "origin"
  },
  "https://wsrv.nl/?url=www.lgh-platz.de/cam/cam61.jpg": {
    "hash": "ce8bfefd3fd956d8ffd6ff4168cb86da6951c9dc",
    "lastChange": 1781941395000,
    "source": "origin"
  },
  "https://wsrv.nl/?url=www.lgh-platz.de/cam/cam91.jpg": {
    "hash": "48604bb35cfff5bc340ef15d6150fe9ed38907d8",
    "lastChange": 1781940869000,
    "source": "origin"
  },
  "https://wsrv.nl/?url=www.lsg-suedwest.de/WebCam/snapshot.jpg": {
    "hash": "53d9ff04b62a5390dda9bc00c8fef0da65f7d554",
    "lastChange": 1781941417000,
    "source": "origin"
  },
  "https://wsrv.nl/?url=www.notschrei-loipe.de/notschrei-loipe.jpg": {
    "hash": "d84a8a7f8338f2dd6ee51b029e75864c9c438ff3",
    "lastChange": 1781941203000,
    "source": "origin"
  },
  "https://wsrv.nl/?url=www.schopfheim.de/webcam/gersbach/video.jpg": {
    "hash": "bcef97106a2e2122ba8e043e3b5bca20e95a7136",
    "lastChange": 1781941458000,
    "source": "origin"
  },
  "https://wsrv.nl/?url=www.ziis.de/cam/current_WE.jpg": {
    "hash": "e327dc52c9fa89b79718aea25408a5daa10d3456",
    "lastChange": 1781941206000,
    "source": "origin"
  },
  "https://wsrv.nl/?url=www.ziis.de/cam/mega.jpg": {
    "hash": "c6e9fd55682e13889dc0c7ce45ba21b750878419",
    "lastChange": 1781941207000,
    "source": "origin"
  }
}
