{
  "https://wsrv.nl/?url=cam.afu-server.de/Klippeneck-CAM1.jpg": {
    "hash": "d4fe9f62b234ed1ae8186186cc6848a4a72a6e9f",
    "lastChange": 1782072258000,
    "source": "origin"
  },
  "https://wsrv.nl/?url=cam.afu-server.de/Klippeneck-CAM3.jpg": {
    "hash": "91b352b434a0e9cb5b063e6b7db09cead23ef94c",
    "lastChange": 1782072259000,
    "source": "origin"
  },
  "https://wsrv.nl/?url=donau-airport.de/donau-airport.de/webcam/cam_neu2.jpg": {
    "hash": "18fe2e8c3837ad4fe36d7030f526bb814b8a59a3",
    "lastChange": 1782072843000,
    "source": "origin"
  },
  "https://wsrv.nl/?url=webcam-gewerbepark.ftp-land-in-sicht.de/snap_c1.jpg": {
    "hash": "9af5595c4977c10f49ff9886be65e52efe07a4ff",
    "lastChange": 1782072888000,
    "source": "origin"
  },
  "https://wsrv.nl/?url=webcam.datacreate.de/feldbergblick/webcam-feldbergblick.jpg": {
    "hash": "5e04dc3e9c0f53a1069c8e33ce8220c959cbb9e5",
    "lastChange": 1782072842000,
    "source": "origin"
  },
  "https://wsrv.nl/?url=www.feldberger-hof.de/static/webcam/fh-webcam.jpg": {
    "hash": "ee8754cb35b07e58a2eac49e7ced5d7e1c752c3f",
    "lastChange": 1782068410000,
    "source": "origin"
  },
  "https://wsrv.nl/?url=www.lgh-platz.de/cam/cam11.jpg": {
    "hash": "28d2fb0f89e7831e2ea3608b7235c8f41f980100",
    "lastChange": 1782030201000,
    "source": "origin"
  },
  "https://wsrv.nl/?url=www.lgh-platz.de/cam/cam21.jpg": {
    "hash": "528fe027d63ee41ce8a0ca5bf0727756c072776b",
    "lastChange": 1782072137000,
    "source": "origin"
  },
  "https://wsrv.nl/?url=www.lgh-platz.de/cam/cam31.jpg": {
    "hash": "658a3e91aaec887b85579443da1738982114a67a",
    "lastChange": 1782072796000,
    "source": "origin"
  },
  "https://wsrv.nl/?url=www.lgh-platz.de/cam/cam41.jpg": {
    "hash": "7cb724fb1babdd83ebb619a2aa0c02ede9a37551",
    "lastChange": 1782072675000,
    "source": "origin"
  },
  "https://wsrv.nl/?url=www.lgh-platz.de/cam/cam51.jpg": {
    "hash": "56cc3c16d02b95091f671f6757934779c286c520",
    "lastChange": 1781861782000,
    "source": "origin"
  },
  "https://wsrv.nl/?url=www.lgh-platz.de/cam/cam61.jpg": {
    "hash": "97461de15e218f5d1ea0f42f0cd89c6a6208deb4",
    "lastChange": 1782072463000,
    "source": "origin"
  },
  "https://wsrv.nl/?url=www.lgh-platz.de/cam/cam91.jpg": {
    "hash": "83c8c97b9ba801bdc4f6842b96353cb702cd2ddc",
    "lastChange": 1782072893000,
    "source": "origin"
  },
  "https://wsrv.nl/?url=www.lsg-suedwest.de/WebCam/snapshot.jpg": {
    "hash": "93006b652dbb978c9a55e0c71926b0c3df10aa73",
    "lastChange": 1782072891000,
    "source": "origin"
  },
  "https://wsrv.nl/?url=www.notschrei-loipe.de/notschrei-loipe.jpg": {
    "hash": "16dc075fd3119f6a3785fdd7c10b01e13b624007",
    "lastChange": 1782072903000,
    "source": "origin"
  },
  "https://wsrv.nl/?url=www.schopfheim.de/webcam/gersbach/video.jpg": {
    "hash": "394c3d28d6cf72a7bec063cba76e320c4f20ac9a",
    "lastChange": 1782072878000,
    "source": "origin"
  },
  "https://wsrv.nl/?url=www.ziis.de/cam/current_WE.jpg": {
    "hash": "9732afc954077b4b49e8787eeb9efc567dfffb81",
    "lastChange": 1782072607000,
    "source": "origin"
  },
  "https://wsrv.nl/?url=www.ziis.de/cam/mega.jpg": {
    "hash": "751d769b121d04efb66216b2c2833c8c229a5097",
    "lastChange": 1782072013000,
    "source": "origin"
  }
}
