{
  "https://wsrv.nl/?url=cam.afu-server.de/Klippeneck-CAM1.jpg": {
    "hash": "c8a2bf98e09a88e3740098f7046c4217b64da520",
    "lastChange": 1779806342000,
    "source": "origin"
  },
  "https://wsrv.nl/?url=cam.afu-server.de/Klippeneck-CAM3.jpg": {
    "hash": "75fd38505a181facc0346e3fa32750aefe500981",
    "lastChange": 1779806342000,
    "source": "origin"
  },
  "https://wsrv.nl/?url=donau-airport.de/donau-airport.de/webcam/cam_neu2.jpg": {
    "hash": "8c2e60d7732367715222637ea517d6deba60c8ae",
    "lastChange": 1779806353000,
    "source": "origin"
  },
  "https://wsrv.nl/?url=webcam-gewerbepark.ftp-land-in-sicht.de/snap_c1.jpg": {
    "hash": "5bd100adc6d8afc7c2322c56e7316bd9bbf69c97",
    "lastChange": 1779806347000,
    "source": "origin"
  },
  "https://wsrv.nl/?url=webcam.datacreate.de/feldbergblick/webcam-feldbergblick.jpg": {
    "hash": "afc985200c75dde48164848e5c53b972de6b0c85",
    "lastChange": 1779806282000,
    "source": "origin"
  },
  "https://wsrv.nl/?url=www.feldberger-hof.de/static/webcam/fh-webcam.jpg": {
    "hash": "a43c580d618ba94c76dad955131793f487f48f51",
    "lastChange": 1779805808000,
    "source": "origin"
  },
  "https://wsrv.nl/?url=www.lgh-platz.de/cam/cam11.jpg": {
    "hash": "7b861e215158fe56566b89cc8af13e09581fbbf7",
    "lastChange": 1779806010000,
    "source": "origin"
  },
  "https://wsrv.nl/?url=www.lgh-platz.de/cam/cam21.jpg": {
    "hash": "70a51f46c496a820d6e65bec8457d52b41042629",
    "lastChange": 1779805941000,
    "source": "origin"
  },
  "https://wsrv.nl/?url=www.lgh-platz.de/cam/cam31.jpg": {
    "hash": "5b13fc1acfd8e6645c6d08d982393634ea9ba86f",
    "lastChange": 1779805885000,
    "source": "origin"
  },
  "https://wsrv.nl/?url=www.lgh-platz.de/cam/cam41.jpg": {
    "hash": "ea9049f018126ea2cd4d1252963a25d794b0635e",
    "lastChange": 1779805879000,
    "source": "origin"
  },
  "https://wsrv.nl/?url=www.lgh-platz.de/cam/cam51.jpg": {
    "hash": "e48440054fa63986d1ede2aa2e0caa6cac2b99ac",
    "lastChange": 1779792867000,
    "source": "origin"
  },
  "https://wsrv.nl/?url=www.lgh-platz.de/cam/cam61.jpg": {
    "hash": "bc41edb05358c62f8c264c8c8d6be95545e848f6",
    "lastChange": 1779805817000,
    "source": "origin"
  },
  "https://wsrv.nl/?url=www.lgh-platz.de/cam/cam91.jpg": {
    "hash": "65d8d78ec1efaf9ea5d53ded71f294b2c65aa846",
    "lastChange": 1779805837000,
    "source": "origin"
  },
  "https://wsrv.nl/?url=www.lsg-suedwest.de/WebCam/snapshot.jpg": {
    "hash": "bc6c3f45443f504d6f0deae34339fb48b5b4eedd",
    "lastChange": 1779806362000,
    "source": "origin"
  },
  "https://wsrv.nl/?url=www.notschrei-loipe.de/notschrei-loipe.jpg": {
    "hash": "25dde36bdff7e4e6360fa306645ff37602c4364a",
    "lastChange": 1779806102000,
    "source": "origin"
  },
  "https://wsrv.nl/?url=www.schopfheim.de/webcam/gersbach/video.jpg": {
    "hash": "ac8c2f7a22a0aeca09cf0266752b90ccd0a80f3c",
    "lastChange": 1779806308000,
    "source": "origin"
  },
  "https://wsrv.nl/?url=www.ziis.de/cam/current_WE.jpg": {
    "hash": "5fb4638ce188de582193052eddc81d003af7174b",
    "lastChange": 1779805803000,
    "source": "origin"
  },
  "https://wsrv.nl/?url=www.ziis.de/cam/mega.jpg": {
    "hash": "76298be835439540e90db2800a8244dd9af37b83",
    "lastChange": 1779805206000,
    "source": "origin"
  }
}
