{
  "https://wsrv.nl/?url=cam.afu-server.de/Klippeneck-CAM1.jpg": {
    "hash": "cb04c5b80174c0e32e0da618dbeca629942b5917",
    "lastChange": 1779935942000,
    "source": "origin"
  },
  "https://wsrv.nl/?url=cam.afu-server.de/Klippeneck-CAM3.jpg": {
    "hash": "c09d68e2e8deec8f9d47f9908db4ca7b35642f3a",
    "lastChange": 1779935942000,
    "source": "origin"
  },
  "https://wsrv.nl/?url=donau-airport.de/donau-airport.de/webcam/cam_neu2.jpg": {
    "hash": "fa212ddea89de97fdf64d684e392431b208c7cff",
    "lastChange": 1779935956000,
    "source": "origin"
  },
  "https://wsrv.nl/?url=webcam-gewerbepark.ftp-land-in-sicht.de/snap_c1.jpg": {
    "hash": "3515d68de214f4e6f08925eae09b2e2cf8ef0018",
    "lastChange": 1779935945000,
    "source": "origin"
  },
  "https://wsrv.nl/?url=webcam.datacreate.de/feldbergblick/webcam-feldbergblick.jpg": {
    "hash": "45fcdf5df23f39d2b9e2b31c1cbcf17213371551",
    "lastChange": 1779935882000,
    "source": "origin"
  },
  "https://wsrv.nl/?url=www.feldberger-hof.de/static/webcam/fh-webcam.jpg": {
    "hash": "0e948a0a7adc892f5255a105aa1e1e608d7bd144",
    "lastChange": 1779908410000,
    "source": "origin"
  },
  "https://wsrv.nl/?url=www.lgh-platz.de/cam/cam11.jpg": {
    "hash": "8bab99282f9a5b900e5c52225731c3b3ce70dc11",
    "lastChange": 1779808415000,
    "source": "origin"
  },
  "https://wsrv.nl/?url=www.lgh-platz.de/cam/cam21.jpg": {
    "hash": "5b0117b699778c3816a2c2311d047d5e4dbe86d0",
    "lastChange": 1779935731000,
    "source": "origin"
  },
  "https://wsrv.nl/?url=www.lgh-platz.de/cam/cam31.jpg": {
    "hash": "b998d8637e5b447f0bcf99f2908195031e922a26",
    "lastChange": 1779935669000,
    "source": "origin"
  },
  "https://wsrv.nl/?url=www.lgh-platz.de/cam/cam41.jpg": {
    "hash": "34fe5cefa8f71f3479bb91b6fd888beb68edd4aa",
    "lastChange": 1779935477000,
    "source": "origin"
  },
  "https://wsrv.nl/?url=www.lgh-platz.de/cam/cam51.jpg": {
    "hash": "a4a0de6d8f421f00cccf0b96545958e400ca519a",
    "lastChange": 1779935483000,
    "source": "origin"
  },
  "https://wsrv.nl/?url=www.lgh-platz.de/cam/cam61.jpg": {
    "hash": "a665639096505e070d6cf01a2cb68d0cb055166f",
    "lastChange": 1779934405000,
    "source": "origin"
  },
  "https://wsrv.nl/?url=www.lgh-platz.de/cam/cam91.jpg": {
    "hash": "165d966614a16e8e31fa87c8bb67280203ac638c",
    "lastChange": 1779935453000,
    "source": "origin"
  },
  "https://wsrv.nl/?url=www.lsg-suedwest.de/WebCam/snapshot.jpg": {
    "hash": "e0db783799317e0130733148f43d5ed2fd6eacf9",
    "lastChange": 1779935914000,
    "source": "origin"
  },
  "https://wsrv.nl/?url=www.notschrei-loipe.de/notschrei-loipe.jpg": {
    "hash": "202d4133fe9f32984402dad35eb9cc427679c32e",
    "lastChange": 1779935702000,
    "source": "origin"
  },
  "https://wsrv.nl/?url=www.schopfheim.de/webcam/gersbach/video.jpg": {
    "hash": "39b8fc1e1fe65e1c2e644e926f55bca7aa9786ff",
    "lastChange": 1779935913000,
    "source": "origin"
  },
  "https://wsrv.nl/?url=www.ziis.de/cam/current_WE.jpg": {
    "hash": "3172a77a13ae0d57d237b03fec178f1e63729e7b",
    "lastChange": 1779935405000,
    "source": "origin"
  },
  "https://wsrv.nl/?url=www.ziis.de/cam/mega.jpg": {
    "hash": "208d71a18026c969be408902c53b0a6f03848745",
    "lastChange": 1779934806000,
    "source": "origin"
  }
}
