{
  "https://wsrv.nl/?url=cam.afu-server.de/Klippeneck-CAM1.jpg": {
    "hash": "d8c8f301a27d49b4245761f31905e6b9cbfb8986",
    "lastChange": 1781941756000,
    "source": "origin"
  },
  "https://wsrv.nl/?url=cam.afu-server.de/Klippeneck-CAM3.jpg": {
    "hash": "bc7e890081cd20cb5282d0e61043b70fdd7eb75b",
    "lastChange": 1781941756000,
    "source": "origin"
  },
  "https://wsrv.nl/?url=donau-airport.de/donau-airport.de/webcam/cam_neu2.jpg": {
    "hash": "83f191270529b630cdcbbbb2ed534a0eadba9d21",
    "lastChange": 1781941754000,
    "source": "origin"
  },
  "https://wsrv.nl/?url=webcam-gewerbepark.ftp-land-in-sicht.de/snap_c1.jpg": {
    "hash": "ac50a4aa660069aad562716d8c0bf783860a8ed9",
    "lastChange": 1781941760000,
    "source": "origin"
  },
  "https://wsrv.nl/?url=webcam.datacreate.de/feldbergblick/webcam-feldbergblick.jpg": {
    "hash": "ffbb79b1ceeabd0fced9963832dcf7badb5cf242",
    "lastChange": 1781941682000,
    "source": "origin"
  },
  "https://wsrv.nl/?url=www.feldberger-hof.de/static/webcam/fh-webcam.jpg": {
    "hash": "a3ea143113b949af01882892ab4690dc42516b61",
    "lastChange": 1781941208000,
    "source": "origin"
  },
  "https://wsrv.nl/?url=www.lgh-platz.de/cam/cam11.jpg": {
    "hash": "7e3ed9128bc5a05a5e92fe232900385f3ad222cb",
    "lastChange": 1781941562000,
    "source": "origin"
  },
  "https://wsrv.nl/?url=www.lgh-platz.de/cam/cam21.jpg": {
    "hash": "4432b620ce5f67dd9ff5f8e060c7c4e9ef273d7a",
    "lastChange": 1781941338000,
    "source": "origin"
  },
  "https://wsrv.nl/?url=www.lgh-platz.de/cam/cam31.jpg": {
    "hash": "ed46c174d7e5c8bd7ae2677f671b87c7aa6639ed",
    "lastChange": 1781941211000,
    "source": "origin"
  },
  "https://wsrv.nl/?url=www.lgh-platz.de/cam/cam41.jpg": {
    "hash": "b8b7e5e79ef35d16f56f9ce776d2c9ee43a00462",
    "lastChange": 1781941273000,
    "source": "origin"
  },
  "https://wsrv.nl/?url=www.lgh-platz.de/cam/cam51.jpg": {
    "hash": "56cc3c16d02b95091f671f6757934779c286c520",
    "lastChange": 1781861782000,
    "source": "origin"
  },
  "https://wsrv.nl/?url=www.lgh-platz.de/cam/cam61.jpg": {
    "hash": "ce8bfefd3fd956d8ffd6ff4168cb86da6951c9dc",
    "lastChange": 1781941395000,
    "source": "origin"
  },
  "https://wsrv.nl/?url=www.lgh-platz.de/cam/cam91.jpg": {
    "hash": "718aa1821a0f27af4a3c5136ae51fe639bf4f232",
    "lastChange": 1781941475000,
    "source": "origin"
  },
  "https://wsrv.nl/?url=www.lsg-suedwest.de/WebCam/snapshot.jpg": {
    "hash": "ac518e192c65757a395af0227117b64e1a7e853e",
    "lastChange": 1781941718000,
    "source": "origin"
  },
  "https://wsrv.nl/?url=www.notschrei-loipe.de/notschrei-loipe.jpg": {
    "hash": "dc3c6aef3333a17be7bf7e120e1c93bc5607d784",
    "lastChange": 1781941502000,
    "source": "origin"
  },
  "https://wsrv.nl/?url=www.schopfheim.de/webcam/gersbach/video.jpg": {
    "hash": "4452d20cfedaa6c82f27ec422bc43c9aafa9ee64",
    "lastChange": 1781941757000,
    "source": "origin"
  },
  "https://wsrv.nl/?url=www.ziis.de/cam/current_WE.jpg": {
    "hash": "e327dc52c9fa89b79718aea25408a5daa10d3456",
    "lastChange": 1781941206000,
    "source": "origin"
  },
  "https://wsrv.nl/?url=www.ziis.de/cam/mega.jpg": {
    "hash": "c6e9fd55682e13889dc0c7ce45ba21b750878419",
    "lastChange": 1781941207000,
    "source": "origin"
  }
}
